miso_plot/__init__.py
miso_plot/core.py
miso_plot/palettes.py
miso_plot/plotting.py
miso_plot-0.1.2.dist-info/licenses/LICENSE
miso_plot-0.1.2.dist-info/METADATA
miso_plot-0.1.2.dist-info/WHEEL
miso_plot-0.1.2.dist-info/top_level.txt
miso_plot-0.1.2.dist-info/RECORD
