Metadata-Version: 2.4
Name: miso-plot
Version: 0.1.2
Summary: Simple visualization tool for clustered high-density data.
Author-email: Aleksandra Suwalska <aleksandra.suwalska@polsl.pl>
License: MIT
Project-URL: Homepage, https://github.com/Aleksandra795/miso-plot
Project-URL: Bug Tracker, https://github.com/Aleksandra795/miso-plot/issues
Keywords: visualization,clustering,data science,umap,big data,matplotlib
Classifier: Programming Language :: Python :: 3
Classifier: Operating System :: OS Independent
Requires-Python: >=3.8
License-File: LICENSE
Requires-Dist: numpy>=1.21
Requires-Dist: matplotlib>=3.5
Requires-Dist: pandas>=1.3
Requires-Dist: seaborn>=0.11
Requires-Dist: scikit-learn>=1.0
Provides-Extra: dev
Requires-Dist: pytest; extra == "dev"
Requires-Dist: pytest-cov; extra == "dev"
Dynamic: license-file
